font_ttfa-0.9.1.dist-info/DESCRIPTION.rst
font_ttfa-0.9.1.dist-info/METADATA
font_ttfa-0.9.1.dist-info/RECORD
font_ttfa-0.9.1.dist-info/WHEEL
font_ttfa-0.9.1.dist-info/entry_points.txt
font_ttfa-0.9.1.dist-info/metadata.json
font_ttfa-0.9.1.dist-info/top_level.txt
fontttfa/__init__.py
fontttfa/app.py
fontttfa/settings.py
fontttfa/commands/__init__.py
