Metadata-Version: 2.0
Name: font-ttfa
Version: 0.9.1
Summary: A command line TTFA table reporting tool for fonts hinted with ttfautohint
Home-page: https://github.com/source-foundry/font-ttfa
Author: Christopher Simpkins
Author-email: chris@sourcefoundry.org
License: MIT license
Keywords: font,fonts,typeface,typography,type,type design,type development,hinting,ttf,TrueType,instructions,ttfautohint,ttfa
Platform: any
Classifier: Intended Audience :: End Users/Desktop
Classifier: Development Status :: 4 - Beta
Classifier: Natural Language :: English
Classifier: License :: OSI Approved :: MIT License
Classifier: Programming Language :: Python
Classifier: Programming Language :: Python :: 2
Classifier: Programming Language :: Python :: 3
Classifier: Operating System :: MacOS :: MacOS X
Classifier: Operating System :: POSIX
Classifier: Operating System :: Unix
Classifier: Operating System :: Microsoft :: Windows
Requires-Dist: Naked
Requires-Dist: commandlines
Requires-Dist: fonttools
